prefecto/__init__.py
prefecto/_version.py
prefecto/blocks.py
prefecto/logging.py
prefecto/states.py
prefecto/concurrency/__init__.py
prefecto/concurrency/batch_task.py
prefecto/concurrency/kill_switch.py
prefecto/ext/__init__.py
prefecto/ext/snowflake.py
prefecto-1.1.1.dist-info/LICENSE
prefecto-1.1.1.dist-info/METADATA
prefecto-1.1.1.dist-info/WHEEL
prefecto-1.1.1.dist-info/top_level.txt
prefecto-1.1.1.dist-info/RECORD
