Metadata-Version: 2.1
Name: prefecto
Version: 1.1.1
Summary: Tools for supporting Prefect development.
Author-email: Dominic Tarro <dtarro@oxfordeconomics.com>
License: MIT License
Project-URL: Documentation, https://dominictarro.github.io/prefecto/
Project-URL: Repository, https://github.com/dominictarro/prefecto
Keywords: prefect,utilities
Classifier: Natural Language :: English
Classifier: Intended Audience :: Developers
Classifier: Intended Audience :: System Administrators
Classifier: License :: OSI Approved :: MIT License
Classifier: Programming Language :: Python :: 3 :: Only
Classifier: Programming Language :: Python :: 3.10
Classifier: Programming Language :: Python :: 3.11
Classifier: Programming Language :: Python :: 3.12
Classifier: Topic :: Software Development :: Libraries
Requires-Python: >=3.10
License-File: LICENSE
Requires-Dist: prefect >=2.10.0
Provides-Extra: snowflake
Requires-Dist: coolname >=2.2.0 ; extra == 'snowflake'
Requires-Dist: snowflake-connector-python >=3.0.0 ; extra == 'snowflake'
